odoo/addons/auth_impersonate_user/LICENSE
odoo/addons/auth_impersonate_user/README.rst
odoo/addons/auth_impersonate_user/__init__.py
odoo/addons/auth_impersonate_user/__manifest__.py
odoo/addons/auth_impersonate_user/controllers/__init__.py
odoo/addons/auth_impersonate_user/controllers/main.py
odoo/addons/auth_impersonate_user/demo/res_users.xml
odoo/addons/auth_impersonate_user/i18n/de.po
odoo/addons/auth_impersonate_user/i18n/de_CH.po
odoo/addons/auth_impersonate_user/images/screen.png
odoo/addons/auth_impersonate_user/models/__init__.py
odoo/addons/auth_impersonate_user/models/res_users.py
odoo/addons/auth_impersonate_user/security/security.xml
odoo/addons/auth_impersonate_user/static/description/icon.png
odoo/addons/auth_impersonate_user/static/description/index.html
odoo/addons/auth_impersonate_user/tests/TEST_INSTRUCTIONS.rst
odoo/addons/auth_impersonate_user/views/res_users.xml
odoo_addon_auth_impersonate_user-18.0.1.0.0.8.dist-info/METADATA
odoo_addon_auth_impersonate_user-18.0.1.0.0.8.dist-info/WHEEL
odoo_addon_auth_impersonate_user-18.0.1.0.0.8.dist-info/top_level.txt
odoo_addon_auth_impersonate_user-18.0.1.0.0.8.dist-info/RECORD
